django_simpletwitchauth-1.0.dist-info/DESCRIPTION.rst
django_simpletwitchauth-1.0.dist-info/LICENSE.txt
django_simpletwitchauth-1.0.dist-info/METADATA
django_simpletwitchauth-1.0.dist-info/RECORD
django_simpletwitchauth-1.0.dist-info/WHEEL
django_simpletwitchauth-1.0.dist-info/metadata.json
django_simpletwitchauth-1.0.dist-info/top_level.txt
twitch_auth/__init__.py
twitch_auth/admin.py
twitch_auth/app_settings.py
twitch_auth/apps.py
twitch_auth/backends.py
twitch_auth/fields.py
twitch_auth/models.py
twitch_auth/urls.py
twitch_auth/utils.py
twitch_auth/views.py
twitch_auth/migrations/0001_initial.py
twitch_auth/migrations/0002_auto_20170605_0003.py
twitch_auth/migrations/__init__.py
